srlp/__init__.py
srlp-0.0.1.dist-info/METADATA
srlp-0.0.1.dist-info/WHEEL
srlp-0.0.1.dist-info/licenses/license.md
srlp-0.0.1.dist-info/RECORD
